sequence_alignment_by_cross_correlation/__init__.py
sequence_alignment_by_cross_correlation/sequence_alignment_by_cross_correlation.py
sequence_alignment_by_cross_correlation-0.1.0.dist-info/AUTHORS.rst
sequence_alignment_by_cross_correlation-0.1.0.dist-info/LICENSE
sequence_alignment_by_cross_correlation-0.1.0.dist-info/METADATA
sequence_alignment_by_cross_correlation-0.1.0.dist-info/WHEEL
sequence_alignment_by_cross_correlation-0.1.0.dist-info/top_level.txt
sequence_alignment_by_cross_correlation-0.1.0.dist-info/RECORD
