Metadata-Version: 2.1
Name: sequence-alignment-by-cross-correlation
Version: 0.1.0
Summary: An implementation of sequence alignment on the basis of cross-correlation technique
Home-page: https://github.com/kuhjuice/sequence_alignment_by_cross_correlation
Author: Bo Kern
Author-email: kern@campus.tu-berlin.de
License: MIT license
Keywords: sequence_alignment_by_cross_correlation
Classifier: Development Status :: 2 - Pre-Alpha
Classifier: Intended Audience :: Developers
Classifier: License :: OSI Approved :: MIT License
Classifier: Natural Language :: English
Classifier: Programming Language :: Python :: 3
Classifier: Programming Language :: Python :: 3.6
Classifier: Programming Language :: Python :: 3.7
Classifier: Programming Language :: Python :: 3.8
Requires-Python: >=3.6
License-File: LICENSE
License-File: AUTHORS.rst
Requires-Dist: typer
Requires-Dist: rich
Requires-Dist: numpy
Requires-Dist: matplotlib
